mdvl.py
mdvl-2017.7.16.7.dist-info/DESCRIPTION.rst
mdvl-2017.7.16.7.dist-info/METADATA
mdvl-2017.7.16.7.dist-info/RECORD
mdvl-2017.7.16.7.dist-info/WHEEL
mdvl-2017.7.16.7.dist-info/entry_points.txt
mdvl-2017.7.16.7.dist-info/metadata.json
mdvl-2017.7.16.7.dist-info/top_level.txt
